fastapi_extend/__init__.py
fastapi_extend/fastapi_jwt/__init__.py
fastapi_extend/pagenator/__init__.py
fastapi_extend/serializer/__init__.py
fastapi_extend/utils/__init__.py
fastapi_extend/utils/singleton_pattern.py
fastapi_extend/utils/task.py
fastapi_extend/utils/value_dispatch.py
fastapi_extend-0.1.3.dist-info/METADATA
fastapi_extend-0.1.3.dist-info/WHEEL
fastapi_extend-0.1.3.dist-info/top_level.txt
fastapi_extend-0.1.3.dist-info/RECORD
